Metadata-Version: 2.1
Name: jaspice
Version: 0.0.1
Summary: Evaluation code for machine-generated image captions in Japanese.
Home-page: https://github.com/keio-smilab23/JaSPICE
Author: Yuiga Wada
Author-email: yuigawada@gmail.com
License: BSD-3-Clause-Clear
Platform: UNKNOWN
Classifier: Programming Language :: Python :: 3
Classifier: Operating System :: OS Independent
Requires-Python: >=3.6
